safe_callback/__init__.py
safe_callback-0.0.5.dist-info/LICENSE
safe_callback-0.0.5.dist-info/METADATA
safe_callback-0.0.5.dist-info/WHEEL
safe_callback-0.0.5.dist-info/top_level.txt
safe_callback-0.0.5.dist-info/RECORD
